ry_tool/__init__.py
ry_tool/__main__.py
ry_tool/_cli.py
ry_tool/app.py
ry_tool/context.py
ry_tool/executor.py
ry_tool/installer.py
ry_tool/loader.py
ry_tool/matcher.py
ry_tool/parser.py
ry_tool/template.py
ry_tool/utils.py
ry_tool-1.3.0.dist-info/WHEEL
ry_tool-1.3.0.dist-info/entry_points.txt
ry_tool-1.3.0.dist-info/METADATA
ry_tool-1.3.0.dist-info/RECORD
