Metadata-Version: 2.3
Name: ry-tool
Version: 1.3.0
Summary: Pure YAML command orchestrator - CI/CD for humans
Author: Fredrik Angelsen
Author-email: Fredrik Angelsen <fredrikangelsen@gmail.com>
Requires-Dist: pyyaml>=6.0
Requires-Python: >=3.12
